LICENSE
MANIFEST.in
README.md
setup.py
bin/cosmosis
bin/cosmosis-ini-from-output
bin/cosmosis-py2
bin/cosmosis-py3
bin/cosmosis-sample-fisher
bin/postprocess
bin/postprocess-py3
cosmosis/Makefile
cosmosis/__init__.py
cosmosis/compilers.py
cosmosis/configure.py
cosmosis/constants.py
cosmosis/gaussian_likelihood.py
cosmosis/main.py
cosmosis/names.py
cosmosis/postprocess.py
cosmosis/version.py
cosmosis/config/compilers.mk
cosmosis/config/subdirs.mk
cosmosis/datablock/Makefile
cosmosis/datablock/__init__.py
cosmosis/datablock/c_datablock.cc
cosmosis/datablock/c_datablock.h
cosmosis/datablock/clamp.hh
cosmosis/datablock/cosmosis_constants.h
cosmosis/datablock/cosmosis_modules.F90
cosmosis/datablock/cosmosis_section_names.F90
cosmosis/datablock/cosmosis_types.F90
cosmosis/datablock/cosmosis_wrappers.F90
cosmosis/datablock/datablock.cc
cosmosis/datablock/datablock.hh
cosmosis/datablock/datablock_logging.cc
cosmosis/datablock/datablock_logging.h
cosmosis/datablock/datablock_status.h
cosmosis/datablock/datablock_types.h
cosmosis/datablock/entry.cc
cosmosis/datablock/entry.hh
cosmosis/datablock/exceptions.hh
cosmosis/datablock/generate_sections.py
cosmosis/datablock/libcosmosis.so
cosmosis/datablock/ndarray.hh
cosmosis/datablock/section.cc
cosmosis/datablock/section.hh
cosmosis/datablock/section_names.h
cosmosis/datablock/section_names.txt
cosmosis/datablock/cosmosis_py/__init__.py
cosmosis/datablock/cosmosis_py/block.py
cosmosis/datablock/cosmosis_py/dbt_types.py
cosmosis/datablock/cosmosis_py/errors.py
cosmosis/datablock/cosmosis_py/lib.py
cosmosis/datablock/cosmosis_py/section_names.py
cosmosis/datablock/cosmosis_py/test.py
cosmosis/output/__init__.py
cosmosis/output/cosmomc_output.py
cosmosis/output/fits_output.py
cosmosis/output/in_memory_output.py
cosmosis/output/null_output.py
cosmosis/output/output_base.py
cosmosis/output/test_cosmomc_output.py
cosmosis/output/test_text_output.py
cosmosis/output/text_output.py
cosmosis/output/utils.py
cosmosis/plotting/__init__.py
cosmosis_standalone.egg-info/PKG-INFO
cosmosis_standalone.egg-info/SOURCES.txt
cosmosis_standalone.egg-info/dependency_links.txt
cosmosis_standalone.egg-info/requires.txt
cosmosis_standalone.egg-info/top_level.txt
