Metadata-Version: 1.0
Name: cosmosis-standalone
Version: 0.2.2
Summary: A testbed stand-alone installation of the CosmoSIS project. Not ready for primetime!
Home-page: https://bitbucket.org/joezuntz/cosmosis
Author: Joe Zuntz
Author-email: joezuntz@googlemail.com
License: UNKNOWN
Platform: UNKNOWN
